ai_models_fourcastnetv2_gfs/__init__.py
ai_models_fourcastnetv2_gfs/model.py
ai_models_fourcastnetv2_gfs/fourcastnetv2/__init__.py
ai_models_fourcastnetv2_gfs/fourcastnetv2/activations.py
ai_models_fourcastnetv2_gfs/fourcastnetv2/contractions.py
ai_models_fourcastnetv2_gfs/fourcastnetv2/layers.py
ai_models_fourcastnetv2_gfs/fourcastnetv2/sfnonet.py
ai_models_fourcastnetv2_gfs-0.0.7.dist-info/licenses/LICENSE
ai_models_fourcastnetv2_gfs-0.0.7.dist-info/licenses/LICENSE_FourCastNetv2
ai_models_fourcastnetv2_gfs-0.0.7.dist-info/METADATA
ai_models_fourcastnetv2_gfs-0.0.7.dist-info/WHEEL
ai_models_fourcastnetv2_gfs-0.0.7.dist-info/entry_points.txt
ai_models_fourcastnetv2_gfs-0.0.7.dist-info/top_level.txt
ai_models_fourcastnetv2_gfs-0.0.7.dist-info/zip-safe
ai_models_fourcastnetv2_gfs-0.0.7.dist-info/RECORD
